saltdash/__init__.py
saltdash/urls.py
saltdash/wsgi.py
saltdash/core/__init__.py
saltdash/core/middleware.py
saltdash/core/server.py
saltdash/dash/__init__.py
saltdash/dash/admin.py
saltdash/dash/models.py
saltdash/dash/urls.py
saltdash/dash/views.py
saltdash/dash/management/__init__.py
saltdash/dash/management/commands/__init__.py
saltdash/dash/management/commands/purge_job_cache.py
saltdash/dash/management/commands/serve.py
saltdash/dash/migrations/0001_initial.py
saltdash/dash/migrations/__init__.py
saltdash/dash/templatetags/__init__.py
saltdash/dash/templatetags/dash_tags.py
saltdash/dash/tests/__init__.py
saltdash/dash/tests/test_models.py
saltdash/dash/tests/test_states.py
saltdash/dash/tests/test_templatetags.py
saltdash/settings/__init__.py
saltdash/settings/_logging.py
saltdash/static/app.20f81a45a2d9.css
saltdash/static/app.20f81a45a2d9.css.gz
saltdash/static/app.520257ee554b.js
saltdash/static/app.520257ee554b.js.gz
saltdash/static/app.62b6c1e58140.js
saltdash/static/app.62b6c1e58140.js.gz
saltdash/static/app.css
saltdash/static/app.css.398044fa1b9b.map
saltdash/static/app.css.398044fa1b9b.map.gz
saltdash/static/app.css.gz
saltdash/static/app.css.map
saltdash/static/app.css.map.gz
saltdash/static/app.js
saltdash/static/app.js.049cad792e1b.map
saltdash/static/app.js.049cad792e1b.map.gz
saltdash/static/app.js.993a1d4ed523.map
saltdash/static/app.js.993a1d4ed523.map.gz
saltdash/static/app.js.gz
saltdash/static/app.js.map
saltdash/static/app.js.map.gz
saltdash/static/staticfiles.json
saltdash/static/admin/css/autocomplete.781713f30664.css
saltdash/static/admin/css/autocomplete.781713f30664.css.gz
saltdash/static/admin/css/autocomplete.css
saltdash/static/admin/css/autocomplete.css.gz
saltdash/static/admin/css/base.41c06691d585.css
saltdash/static/admin/css/base.94893682937c.css
saltdash/static/admin/css/base.ae33e6383baa.css
saltdash/static/admin/css/base.ae33e6383baa.css.gz
saltdash/static/admin/css/base.css
saltdash/static/admin/css/base.css.gz
saltdash-0.9.9.dist-info/LICENSE
saltdash-0.9.9.dist-info/METADATA
saltdash-0.9.9.dist-info/WHEEL
saltdash-0.9.9.dist-info/entry_points.txt
saltdash-0.9.9.dist-info/top_level.txt
saltdash-0.9.9.dist-info/RECORD
