Metadata-Version: 2.1
Name: saltdash
Version: 0.9.9
Summary: A Dahsboard for SaltStack's Job Cache
Home-page: https://github.com/lincolnloop/saltdash/
Author: Peter Baumgartner
Author-email: pete@lincolnloop.com
License: MIT
Keywords: salt,dashboard
Platform: UNKNOWN
Classifier: Development Status :: 5 - Production/Stable
Classifier: Environment :: Web Environment
Classifier: License :: OSI Approved :: MIT License
Classifier: Operating System :: OS Independent
Classifier: Programming Language :: Python
Classifier: Programming Language :: Python :: 3.5
Classifier: Programming Language :: Python :: 3.6
Classifier: Programming Language :: Python :: 3.7
Classifier: Framework :: Django
Requires-Dist: django (==2.2.12)
Requires-Dist: django-alive (<1.1)
Requires-Dist: dj-database-url (==0.5.0)
Requires-Dist: goodconf[yaml] (<1.1)
Requires-Dist: psycopg2-binary (==2.8.5)
Requires-Dist: python-json-logger (==0.1.11)
Requires-Dist: sentry-sdk (==0.14.3)
Requires-Dist: social-auth-app-django (==3.1.0)
Requires-Dist: pytest-cov (==2.8.1)
Requires-Dist: pytest-django (==3.9.0)
Requires-Dist: model-bakery (==1.1.0)
Requires-Dist: waitress (==1.4.3)
Requires-Dist: whitenoise (==5.0.1)
